scraptrawler/deck.py
scraptrawler/extractor.py
scraptrawler/scraper/base.py
scraptrawler/scraper/melee.py
scraptrawler/scraper/mtgo.py
scraptrawler/utils.py
scraptrawler-1.0.1.dist-info/METADATA
scraptrawler-1.0.1.dist-info/WHEEL
scraptrawler-1.0.1.dist-info/RECORD
